plone.app.fhirfield-4.2.1-py3.7-nspkg.pth
plone/app/fhirfield/__init__.py
plone/app/fhirfield/compat.py
plone/app/fhirfield/configure.zcml
plone/app/fhirfield/deserializer.py
plone/app/fhirfield/deserializer.zcml
plone/app/fhirfield/error.py
plone/app/fhirfield/error.zcml
plone/app/fhirfield/field.py
plone/app/fhirfield/handler.py
plone/app/fhirfield/handler.zcml
plone/app/fhirfield/helpers.py
plone/app/fhirfield/interfaces.py
plone/app/fhirfield/marshaler.py
plone/app/fhirfield/marshaler.zcml
plone/app/fhirfield/permissions.zcml
plone/app/fhirfield/schemaeditor.py
plone/app/fhirfield/schemaeditor.zcml
plone/app/fhirfield/serializer.py
plone/app/fhirfield/serializer.zcml
plone/app/fhirfield/setuphandlers.py
plone/app/fhirfield/testing.py
plone/app/fhirfield/upgrades.py
plone/app/fhirfield/upgrades.zcml
plone/app/fhirfield/value.py
plone/app/fhirfield/widget.py
plone/app/fhirfield/widget.zcml
plone/app/fhirfield/browser/__init__.py
plone/app/fhirfield/browser/configure.zcml
plone/app/fhirfield/browser/overrides/.gitkeep
plone/app/fhirfield/browser/static/.gitkeep
plone/app/fhirfield/browser/static/FHIR/HL7/ResourceList/STU3.json
plone/app/fhirfield/browser/static/FHIR/HL7/search/FHIR-Search-Parameter-Registry-searchable.json
plone/app/fhirfield/browser/static/FHIR/HL7/search/FHIR-Search-Parameter-Registry.json
plone/app/fhirfield/browser/static/css/jquery.json-viewer.css
plone/app/fhirfield/browser/static/js/jquery.json-viewer.js
plone/app/fhirfield/locales/plone.app.fhirfield.pot
plone/app/fhirfield/locales/update.sh
plone/app/fhirfield/profiles/default/metadata.xml
plone/app/fhirfield/profiles/default/registry.xml
plone/app/fhirfield/profiles/default/rolemap.xml
plone/app/fhirfield/profiles/testing/types.xml
plone/app/fhirfield/profiles/testing/types/FFChargeItem.xml
plone/app/fhirfield/profiles/testing/types/FFDevice.xml
plone/app/fhirfield/profiles/testing/types/FFDeviceRequest.xml
plone/app/fhirfield/profiles/testing/types/FFEncounter.xml
plone.app.fhirfield-4.2.1.dist-info/LICENSE.GPL
plone.app.fhirfield-4.2.1.dist-info/LICENSE.rst
plone.app.fhirfield-4.2.1.dist-info/METADATA
plone.app.fhirfield-4.2.1.dist-info/WHEEL
plone.app.fhirfield-4.2.1.dist-info/entry_points.txt
plone.app.fhirfield-4.2.1.dist-info/namespace_packages.txt
plone.app.fhirfield-4.2.1.dist-info/top_level.txt
plone.app.fhirfield-4.2.1.dist-info/RECORD
