Metadata-Version: 2.1
Name: plone.app.fhirfield
Version: 4.2.1
Summary: FHIR field for Plone
Home-page: https://pypi.org/project/plone.app.fhirfield/
Author: Md Nazrul Islam
Author-email: email2nazrul@gmail.com
License: GPL version 2
Keywords: Python Plone Zope FHIR Field
Platform: UNKNOWN
Classifier: Development Status :: 5 - Production/Stable
Classifier: Environment :: Web Environment
Classifier: Framework :: Plone
Classifier: Framework :: Plone :: 5.2
Classifier: Framework :: Plone :: 5.3
Classifier: Framework :: Plone :: Addon
Classifier: Programming Language :: Python
Classifier: Programming Language :: Python :: 3
Classifier: Programming Language :: Python :: 3.6
Classifier: Programming Language :: Python :: 3.7
Classifier: Programming Language :: Python :: 3.8
Classifier: Programming Language :: Python :: 3.9
Classifier: Operating System :: OS Independent
Classifier: License :: OSI Approved :: GNU General Public License v2 (GPLv2)
Requires-Python: >=3.6
Requires-Dist: setuptools
Requires-Dist: jsonpatch
Requires-Dist: fhirpath (>=0.7.1)
Provides-Extra: test
Requires-Dist: plone.restapi ; extra == 'test'
Requires-Dist: plone.schemaeditor ; extra == 'test'
Requires-Dist: plone.supermodel ; extra == 'test'
Requires-Dist: plone.app.testing ; extra == 'test'
Requires-Dist: plone.testing (>=7.0.1) ; extra == 'test'
Requires-Dist: plone.app.contenttypes ; extra == 'test'
Requires-Dist: plone.app.robotframework[debug] ; extra == 'test'
Requires-Dist: collective.MockMailHost ; extra == 'test'
Requires-Dist: Products.contentmigration ; extra == 'test'
Requires-Dist: requests ; extra == 'test'
Requires-Dist: flake8-bugbear ; extra == 'test'
